intentional_pipecat/__about__.py
intentional_pipecat/__init__.py
intentional_pipecat/bot_structure.py
intentional_pipecat/frame_processor.py
intentional_pipecat/transport.py
intentional_pipecat-0.0.1.dist-info/METADATA
intentional_pipecat-0.0.1.dist-info/WHEEL
intentional_pipecat-0.0.1.dist-info/licenses/LICENSE.txt
intentional_pipecat-0.0.1.dist-info/RECORD
